{
    "node_id": "prism_register_callback",
    "name": "Prism: Register Callback",
    "description": "Registers a Prism callback (e.g. onShotCreated, onProductCreated, onSceneSaved). When the event fires inside Prism, this node emits the `triggered` exec pin and exposes the callback args. Wraps core.callbacks.registerCallback(name, fn).",
    "category": "DCCs",
    "icon_path": "icons/prism_icon.png",
    "inputs": [
        {
            "name": "exec_in",
            "type": "exec"
        },
        {
            "name": "core",
            "type": "any"
        },
        {
            "name": "callback_name",
            "type": "string",
            "widget_type": "dropdown",
            "options": [
                "onShotCreated",
                "onAssetCreated",
                "onProjectCreated",
                "onProjectChanged",
                "onSceneOpen",
                "onSceneSaved",
                "onProductCreated",
                "onMediaCreated",
                "onPublish",
                "onStateManagerOpen"
            ],
            "default": "onShotCreated"
        }
    ],
    "outputs": [
        {
            "name": "exec_out",
            "type": "exec"
        },
        {
            "name": "registered",
            "type": "bool"
        },
        {
            "name": "triggered",
            "type": "exec"
        },
        {
            "name": "args",
            "type": "list"
        },
        {
            "name": "first_arg",
            "type": "any"
        }
    ],
    "python_code": "import asyncio\nfrom src.nodes.base import BaseNode\nfrom src.utils.prism_core import resolve_prism_core\n\nclass PrismRegisterCallbackNode(BaseNode):\n    name = \"Prism: Register Callback\"\n    category = \"DCCs\"\n\n    def __init__(self):\n        super().__init__()\n        self.icon_path = \"icons/prism_icon.png\"\n        self.add_input(\"core\", \"any\")\n        self.add_input(\"callback_name\", \"string\", widget_type=\"dropdown\", options=[\"onShotCreated\",\"onAssetCreated\",\"onProjectCreated\",\"onProjectChanged\",\"onSceneOpen\",\"onSceneSaved\",\"onProductCreated\",\"onMediaCreated\",\"onPublish\",\"onStateManagerOpen\"], default=\"onShotCreated\")\n        self.add_output(\"registered\", \"bool\")\n        self.add_exec_output(\"triggered\")\n        self.add_output(\"args\", \"list\")\n        self.add_output(\"first_arg\", \"any\")\n        self._registered_for = None\n        self._loop = None\n\n    def _on_event(self, *args, **kwargs):\n        # Called by Prism (sync) - schedule async output back into the engine\n        self.parameters['args'] = list(args)\n        self.parameters['first_arg'] = args[0] if args else None\n        self.log_info(f\"Callback fired: {self._registered_for} args={args}\")\n        try:\n            loop = self._loop or asyncio.get_event_loop()\n            asyncio.run_coroutine_threadsafe(self.set_output('triggered', True), loop)\n            asyncio.run_coroutine_threadsafe(self.set_output('args', list(args)), loop)\n            asyncio.run_coroutine_threadsafe(self.set_output('first_arg', args[0] if args else None), loop)\n        except Exception as e:\n            self.log_error(f\"Could not dispatch callback to engine: {e}\")\n\n    async def execute(self, inputs):\n        core = resolve_prism_core(inputs)\n        cb_name = inputs.get('callback_name') or ''\n        if core is None or not cb_name:\n            self.log_error(\"Need PrismCore and callback_name.\")\n            return {'registered': False, 'args': [], 'first_arg': None}\n        try:\n            self._loop = asyncio.get_event_loop()\n            core.callbacks.registerCallback(cb_name, self._on_event, plugin=self)\n            self._registered_for = cb_name\n            self.log_success(f\"Registered callback '{cb_name}'.\")\n            await self.set_output('exec_out', True)\n            return {'registered': True, 'args': [], 'first_arg': None}\n        except Exception as e:\n            self.log_error(f\"registerCallback failed: {e}\")\n            return {'registered': False, 'args': [], 'first_arg': None}\n\ndef register_node():\n    return PrismRegisterCallbackNode\n"
}